plot_field/__init__.py
plot_field/__main__.py
plot_field/plot_field.py
plot_field/vlass_search.py
lofar_vlbi_pipeline-2024.1.0.dist-info/LICENSE
lofar_vlbi_pipeline-2024.1.0.dist-info/METADATA
lofar_vlbi_pipeline-2024.1.0.dist-info/WHEEL
lofar_vlbi_pipeline-2024.1.0.dist-info/entry_points.txt
lofar_vlbi_pipeline-2024.1.0.dist-info/top_level.txt
lofar_vlbi_pipeline-2024.1.0.dist-info/RECORD
