Metadata-Version: 2.1
Name: lofar-vlbi-pipeline
Version: 2024.1.0
Summary: lofar-vlbi-pipeline containing the cli tool plot_field
License:                     GNU GENERAL PUBLIC LICENSE
Project-URL: Repository, https://github.com/LOFAR-VLBI/lofar-vlbi-pipeline
Keywords: radio,astronomy,VLBI,LOFAR
Requires-Python: >=3.13
License-File: LICENSE
Requires-Dist: astropy>=7.0.0
Requires-Dist: matplotlib>=3.9.3
Requires-Dist: pyvo>=1.6
Requires-Dist: requests>=2.32.3
Requires-Dist: scipy>=1.14.1
